{
    "asset": {
        "id": "5266e3befde4fc143d7835a27cec994c",
        "format": "466667",
        "state": 2,
        "type": 3,
        "name": "orochi.mp4#t=5.466667",
        "path": "file:D:/%23WorkSpace/ObjectDetection_JetsonNano_Tensorflow/annotationAndTraining/car/annotation/source/orochi.mp4#t=5.466667",
        "size": {
            "width": 480,
            "height": 270
        },
        "parent": {
            "format": "mp4",
            "id": "9f60f090b5a2731176f5db2fa45e9ca7",
            "name": "orochi.mp4",
            "path": "file:D:/%23WorkSpace/ObjectDetection_JetsonNano_Tensorflow/annotationAndTraining/car/annotation/source/orochi.mp4",
            "size": {
                "width": 480,
                "height": 270
            },
            "state": 1,
            "type": 2
        },
        "timestamp": 5.466667,
        "predicted": true
    },
    "regions": [
        {
            "id": "8LtKv5UtrV",
            "type": "RECTANGLE",
            "tags": [
                "orochi"
            ],
            "boundingBox": {
                "left": 216.3623571395874,
                "top": 83.08686375617981,
                "width": 156.7805528640747,
                "height": 82.46621131896973
            },
            "points": [
                {
                    "x": 216.3623571395874,
                    "y": 83.08686375617981
                },
                {
                    "x": 373.1429100036621,
                    "y": 83.08686375617981
                },
                {
                    "x": 373.1429100036621,
                    "y": 165.55307507514954
                },
                {
                    "x": 216.3623571395874,
                    "y": 165.55307507514954
                }
            ]
        }
    ],
    "version": "2.1.0"
}